issue_manager/__init__.py
issue_manager/main.py
issue_manager/version.py
issue_manager-2024.1.dist-info/METADATA
issue_manager-2024.1.dist-info/WHEEL
issue_manager-2024.1.dist-info/top_level.txt
issue_manager-2024.1.dist-info/RECORD
