Metadata-Version: 2.1
Name: issue-manager
Version: 2024.1
Summary: Buffer for Runtime Issues
Home-page: https://src.koda.cnrs.fr/eric.debreuve/issue-manager/
Author: Eric Debreuve
Author-email: eric.debreuve@cnrs.fr
License: CeCILL-2.1
Project-URL: Documentation, https://src.koda.cnrs.fr/eric.debreuve/issue-manager//-/wikis/home
Project-URL: Source, https://src.koda.cnrs.fr/eric.debreuve/issue-manager/
Keywords: issue,warning,error,manager,management
Classifier: Topic :: Software Development
Classifier: Intended Audience :: Developers
Classifier: License :: OSI Approved :: CEA CNRS Inria Logiciel Libre License, version 2.1 (CeCILL-2.1)
Classifier: Programming Language :: Python :: 3.10
Classifier: Development Status :: 4 - Beta
Requires-Python: >=3.10
Requires-Dist: rich
